odoo9_addon_stock_analytic-9.0.1.0.0-py2.7-nspkg.pth
odoo9_addon_stock_analytic-9.0.1.0.0.dist-info/DESCRIPTION.rst
odoo9_addon_stock_analytic-9.0.1.0.0.dist-info/METADATA
odoo9_addon_stock_analytic-9.0.1.0.0.dist-info/RECORD
odoo9_addon_stock_analytic-9.0.1.0.0.dist-info/WHEEL
odoo9_addon_stock_analytic-9.0.1.0.0.dist-info/metadata.json
odoo9_addon_stock_analytic-9.0.1.0.0.dist-info/namespace_packages.txt
odoo9_addon_stock_analytic-9.0.1.0.0.dist-info/top_level.txt
odoo_addons/stock_analytic/README.rst
odoo_addons/stock_analytic/__init__.py
odoo_addons/stock_analytic/__openerp__.py
odoo_addons/stock_analytic/i18n/ca.po
odoo_addons/stock_analytic/i18n/de.po
odoo_addons/stock_analytic/i18n/el_GR.po
odoo_addons/stock_analytic/i18n/es.po
odoo_addons/stock_analytic/i18n/es_MX.po
odoo_addons/stock_analytic/i18n/fi.po
odoo_addons/stock_analytic/i18n/fr.po
odoo_addons/stock_analytic/i18n/gl.po
odoo_addons/stock_analytic/i18n/hr.po
odoo_addons/stock_analytic/i18n/hr_HR.po
odoo_addons/stock_analytic/i18n/hu.po
odoo_addons/stock_analytic/i18n/it.po
odoo_addons/stock_analytic/i18n/nl.po
odoo_addons/stock_analytic/i18n/pt.po
odoo_addons/stock_analytic/i18n/pt_BR.po
odoo_addons/stock_analytic/i18n/pt_PT.po
odoo_addons/stock_analytic/i18n/ro.po
odoo_addons/stock_analytic/i18n/sk_SK.po
odoo_addons/stock_analytic/i18n/sl.po
odoo_addons/stock_analytic/i18n/tr.po
odoo_addons/stock_analytic/i18n/tr_TR.po
odoo_addons/stock_analytic/i18n/vi_VN.po
odoo_addons/stock_analytic/i18n/zh_CN.po
odoo_addons/stock_analytic/models/__init__.py
odoo_addons/stock_analytic/models/stock.py
odoo_addons/stock_analytic/static/description/icon.png
odoo_addons/stock_analytic/tests/__init__.py
odoo_addons/stock_analytic/tests/test_stock_picking.py
odoo_addons/stock_analytic/views/stock_inventory_views.xml
odoo_addons/stock_analytic/views/stock_move_views.xml
